dockercv/__init__.py
dockercv/dockernode.py
dockercv/hostnode.py
dockercv/utils.py
dockercv-0.0.1.dist-info/DESCRIPTION.rst
dockercv-0.0.1.dist-info/METADATA
dockercv-0.0.1.dist-info/RECORD
dockercv-0.0.1.dist-info/WHEEL
dockercv-0.0.1.dist-info/metadata.json
dockercv-0.0.1.dist-info/top_level.txt
