Metadata-Version: 2.0
Name: dockercv
Version: 0.0.1
Summary: A solution for visualizing Docker-based computer vision applications
Home-page: UNKNOWN
Author: Jonathan Hampton
Author-email: hamptonjc221@gmail.com
License: UNKNOWN
Keywords: docker cv,docker visual
Platform: UNKNOWN
Classifier: Development Status :: 3 - Alpha
Classifier: Programming Language :: Python :: 3
Classifier: Operating System :: Unix
Requires-Dist: posix-ipc
Requires-Dist: numpy
